noiftimer/__init__.py
noiftimer/noiftimer.py
noiftimer/py.typed
noiftimer/stopwatch.py
noiftimer-2.5.0.dist-info/METADATA
noiftimer-2.5.0.dist-info/WHEEL
noiftimer-2.5.0.dist-info/entry_points.txt
noiftimer-2.5.0.dist-info/licenses/LICENSE.txt
noiftimer-2.5.0.dist-info/RECORD
