Metadata-Version: 2.4
Name: noiftimer
Version: 2.5.0
Summary: Timing class for measuring elapsed time and average elapsed time.
Project-URL: Homepage, https://github.com/matt-manes/noiftimer
Project-URL: Documentation, https://github.com/matt-manes/noiftimer/tree/main/docs
Project-URL: Source code, https://github.com/matt-manes/noiftimer/tree/main/src/noiftimer
Author: Matt Manes
License-File: LICENSE.txt
Keywords: timer,timing
Classifier: License :: OSI Approved :: MIT License
Classifier: Operating System :: OS Independent
Classifier: Programming Language :: Python :: 3
Requires-Python: >=3.10
Requires-Dist: loggi
Requires-Dist: printbuddies
Requires-Dist: pytest
Requires-Dist: typing-extensions
